behave_django_steps/__init__.py
behave_django_steps/given/__init__.py
behave_django_steps/given/models/__init__.py
behave_django_steps/given/models/create.py
behave_django_steps/given/models/exist.py
behave_django_steps/given/models/fixtures.py
behave_django_steps/given/models/update.py
behave_django_steps/given/request/__init__.py
behave_django_steps/given/request/authentication.py
behave_django_steps/given/request/authorization.py
behave_django_steps/given/request/context.py
behave_django_steps/given/request/data.py
behave_django_steps/then/__init__.py
behave_django_steps/then/authentication.py
behave_django_steps/then/authorization.py
behave_django_steps/then/models/__init__.py
behave_django_steps/then/models/filter.py
behave_django_steps/then/queries/__init__.py
behave_django_steps/then/queries/performance.py
behave_django_steps/then/response/__init__.py
behave_django_steps/then/response/data.py
behave_django_steps/then/response/status.py
behave_django_steps/when/__init__.py
behave_django_steps/when/fixtures.py
behave_django_steps/when/queries/__init__.py
behave_django_steps/when/queries/performance.py
behave_django_steps/when/request/__init__.py
behave_django_steps/when/request/execute.py
behave_django_steps-0.7.15.dist-info/METADATA
behave_django_steps-0.7.15.dist-info/WHEEL
behave_django_steps-0.7.15.dist-info/licenses/LICENSE
behave_django_steps-0.7.15.dist-info/RECORD
