Metadata-Version: 2.3
Name: behave-django-steps
Version: 0.7.15
Summary: Boilerplate steps for testing Django with Behave
Project-URL: Homepage, https://github.com/BillSchumacher/behave-django-steps
Project-URL: Bug Tracker, https://github.com/BillSchumacher/behave-django-steps/issues
Author-email: Bill Schumacher <34168009+BillSchumacher@users.noreply.github.com>
License-Expression: MIT
License-File: LICENSE
Classifier: Development Status :: 4 - Beta
Classifier: Environment :: Web Environment
Classifier: Framework :: Django
Classifier: Framework :: Django :: 3.1
Classifier: Framework :: Django :: 3.2
Classifier: Framework :: Django :: 4.0
Classifier: Framework :: Django :: 4.1
Classifier: Framework :: Django :: 4.2
Classifier: License :: OSI Approved :: MIT License
Classifier: Operating System :: OS Independent
Classifier: Programming Language :: Python :: 3
Classifier: Programming Language :: Python :: 3 :: Only
Classifier: Programming Language :: Python :: 3.9
Classifier: Programming Language :: Python :: 3.10
Classifier: Programming Language :: Python :: 3.11
Classifier: Topic :: Internet :: WWW/HTTP
Requires-Python: >=3.8
Requires-Dist: behave-django
Requires-Dist: django
